{
  "white": "#fff",
  "silver": "#f1f3f5",
  "black": "#212529",
  "gray": [
    "#e2e5e9",
    "#d8dde1",
    "#ced4da",
    "#abb1b7",
    "#898e93"
  ],
  "teal": [
    "#88e8cb",
    "#60e1ba",
    "#38d9a9",
    "#33b58f",
    "#2f9176"
  ],
  "cyan": [
    "#89dfe9",
    "#62d4e2",
    "#3bc9db",
    "#36a8b7",
    "#318794"
  ],
  "blue": [
    "#85c2f6",
    "#5caef3",
    "#339af0",
    "#2f83c8",
    "#2c6ba0"
  ],
  "indigo": [
    "#acbcfd",
    "#90a5fd",
    "#748ffc",
    "#637ad2",
    "#5365a8"
  ],
  "violet": [
    "#c1acfc",
    "#ac91fb",
    "#9775fa",
    "#7f65d0",
    "#6855a6"
  ],
  "grape": [
    "#e9adf7",
    "#e192f5",
    "#da77f2",
    "#b567ca",
    "#9056a2"
  ],
  "pink": [
    "#fab5cd",
    "#f99cbd",
    "#f783ac",
    "#cc7092",
    "#a15d78"
  ],
  "red": [
    "#ec8383",
    "#e65a5a",
    "#e03131",
    "#ba2f2f",
    "#942c2e"
  ],
  "orange": [
    "#ffbe80",
    "#ffa855",
    "#ff922b",
    "#d37c2b",
    "#a6662a"
  ],
  "yellow": [
    "#ffeca3",
    "#ffe685",
    "#ffe066",
    "#d3bb5a",
    "#a6954e"
  ],
  "lime": [
    "#cbee93",
    "#bae96f",
    "#a9e34b",
    "#8ebd44",
    "#73973d"
  ],
  "green": [
    "#97e2a3",
    "#74d985",
    "#51cf66",
    "#47ad5a",
    "#3e8b4e"
  ]
}
